LICENSE
README.md
setup.py
nobunaga/__init__.py
nobunaga/command_line.py
nobunaga/constants.py
nobunaga/evaluator.py
nobunaga/image_printer.py
nobunaga.egg-info/PKG-INFO
nobunaga.egg-info/SOURCES.txt
nobunaga.egg-info/dependency_links.txt
nobunaga.egg-info/entry_points.txt
nobunaga.egg-info/requires.txt
nobunaga.egg-info/top_level.txt
nobunaga/io/__init__.py
nobunaga/io/gt_json.py
nobunaga/io/output_terminal.py
nobunaga/io/plot_util.py
nobunaga/io/pred_json.py
nobunaga/io/visualizer.py
nobunaga/labels/__init__.py
nobunaga/labels/gt_label.py
nobunaga/labels/label.py
nobunaga/labels/nobunaga_image.py
nobunaga/labels/pred_label.py
nobunaga/utils/__init__.py
nobunaga/utils/compute_iou.py