Metadata-Version: 2.1
Name: nobunaga
Version: 0.0.0
Summary: Nobunaga: Object Detection Analyzer
Home-page: https://github.com/FastAccounting/nobunaga
Author: FUJITAKE Masato and Fast Accounting Co., Ltd.
License-File: LICENSE
